bg_helper/__init__.py
bg_helper/tools/__init__.py
bg_helper/tools/_docker.py
bg_helper/tools/_git.py
bg_helper/tools/_grep.py
bg_helper/tools/_pip.py
bg_helper/tools/_ps.py
bg_helper/tools/_pyenv.py
bg_helper/tools/_sql.py
bg_helper/tools/_ssh.py
bg_helper-0.1.24.dist-info/LICENSE.txt
bg_helper-0.1.24.dist-info/METADATA
bg_helper-0.1.24.dist-info/WHEEL
bg_helper-0.1.24.dist-info/top_level.txt
bg_helper-0.1.24.dist-info/RECORD
