Metadata-Version: 2.1
Name: bg-helper
Version: 0.1.24
Summary: CLI helpers for background tasks (shell), docker (databases), git, and SSH
Home-page: https://github.com/kenjyco/bg-helper
Download-URL: https://github.com/kenjyco/bg-helper/tarball/v0.1.24
Author: Ken
Author-email: kenjyco@gmail.com
License: MIT
Keywords: background,shell,git,ssh,docker,pyenv,redis,mongodb,postgres,postgresql,mysql,helper,kenjyco
Platform: UNKNOWN
Classifier: Development Status :: 4 - Beta
Classifier: Environment :: Console
Classifier: Intended Audience :: Developers
Classifier: License :: OSI Approved :: MIT License
Classifier: Operating System :: MacOS :: MacOS X
Classifier: Operating System :: POSIX :: Linux
Classifier: Programming Language :: Python :: 3.5
Classifier: Programming Language :: Python :: 3.6
Classifier: Programming Language :: Python :: 3.7
Classifier: Programming Language :: Python :: 3.8
Classifier: Programming Language :: Python :: 3.9
Classifier: Programming Language :: Python :: 3.10
Classifier: Programming Language :: Python :: 3.11
Classifier: Programming Language :: Python :: 3.12
Classifier: Programming Language :: Python :: 3.13
Classifier: Programming Language :: Python
Classifier: Programming Language :: Unix Shell
Classifier: Topic :: Database
Classifier: Topic :: Software Development :: Libraries
Classifier: Topic :: Utilities
License-File: LICENSE.txt
Requires-Dist: fs-helper
Requires-Dist: input-helper
Requires-Dist: importlib-metadata ; python_version < "3.8"
